setup.cfg
setup.py
crank/__init__.py
crank/dispatcher.py
crank/dispatchstate.py
crank/objectdispatcher.py
crank/restdispatcher.py
crank/util.py
crank.egg-info/PKG-INFO
crank.egg-info/SOURCES.txt
crank.egg-info/dependency_links.txt
crank.egg-info/entry_points.txt
crank.egg-info/top_level.txt
crank.egg-info/zip-safe