Metadata-Version: 1.0
Name: crank
Version: 0.6.1
Summary: Generalization of dispatch mechanism for use across frameworks.
Home-page: UNKNOWN
Author: Christopher Perkins
Author-email: chris@percious.com
License: MIT
Platform: UNKNOWN
